enpass/__init__.py
enpass/base.py
enpass/entropy.py
enpass-0.1.2.dist-info/LICENSE
enpass-0.1.2.dist-info/METADATA
enpass-0.1.2.dist-info/WHEEL
enpass-0.1.2.dist-info/top_level.txt
enpass-0.1.2.dist-info/RECORD
