Metadata-Version: 2.1
Name: enpass
Version: 0.1.2
Summary: Simple entropy password validator.
Home-page: https://github.com/Aresshu/enpass
Author: Andres Ordonez
License: MIT
Keywords: entropy password validator strength
Classifier: Intended Audience :: Developers
Classifier: License :: OSI Approved :: MIT License
Classifier: Natural Language :: English
Classifier: Programming Language :: Python
Classifier: Topic :: Security
Classifier: Topic :: Software Development :: Libraries :: Python Modules
License-File: LICENSE
